README.rst
setup.py
textrazor.py
textrazor.egg-info/PKG-INFO
textrazor.egg-info/SOURCES.txt
textrazor.egg-info/dependency_links.txt
textrazor.egg-info/top_level.txt