Metadata-Version: 1.1
Name: textrazor
Version: 1.2.2
Summary: Official Python SDK for TextRazor (https://textrazor.com).
Home-page: https://textrazor.com/
Author: TextRazor Ltd.
Author-email: toby@textrazor.com
License: MIT
Platform: UNKNOWN
Classifier: License :: OSI Approved :: MIT License
Classifier: Operating System :: OS Independent
Classifier: Programming Language :: Python
Classifier: Programming Language :: Python :: 2.6
Classifier: Topic :: Software Development
